gle/__init__.py
gle/utils.py
gle/envs/__init__.py
gle/envs/castlevania2.py
gle/envs/castlevaniaadventure.py
gle/envs/donkeykongland2.py
gle/envs/donkeykongland3.py
gle/envs/finalfantasyadventure.py
gle/envs/general.py
gle/envs/kirbysdreamland.py
gle/envs/megamandrwilysrevenge.py
gle/envs/megamanxtreme.py
gle/envs/pokemonbluered.py
gle/envs/pokemongoldsilver.py
gle/envs/solomonsclub.py
gle/envs/supermarioland.py
gle/envs/tetris.py
gle/envs/zeldalinksawakening.py
gle/human/__init__.py
gle/human/collect.py
gle/human/data.py
gle/human/visualization.py
"gle/roms/Castlevania Adventure, The (E) [!].gb"
gle/roms/Castlevania II - Belmont's Revenge (U) [!].gb
gle/roms/Donkey Kong Land (U) [S][!].gb
gle/roms/Donkey Kong Land 2 (UE) [S][!].gb
gle/roms/Donkey Kong Land III (U) [S][!].gb
gle/roms/Final Fantasy Adventure (USA).gb
"gle/roms/Kirby's Dream Land (USA, Europe).gb"
"gle/roms/Legend of Zelda, The - Link's Awakening (U) (V1.2) [!].gb"
gle/roms/Mega Man - Dr. Wily's Revenge (E) [!].gb
gle/roms/Mega Man Xtreme (U) [C][!].gbc
gle/roms/Pokemon - Silver Version (UE) [C][!].gbc
gle/roms/Pokemon Red (UE) [S][!].gb
gle/roms/Solomon's Club (UE) [!].gb
gle/roms/Super Mario Land (JUE) (V1.1) [!].gb
gle/roms/Tetris (JUE) (V1.1) [!].gb
GameBoyLearningEnvironment-1.0.1.dist-info/LICENSE
GameBoyLearningEnvironment-1.0.1.dist-info/METADATA
GameBoyLearningEnvironment-1.0.1.dist-info/WHEEL
GameBoyLearningEnvironment-1.0.1.dist-info/top_level.txt
GameBoyLearningEnvironment-1.0.1.dist-info/RECORD
