Metadata-Version: 2.1
Name: GameBoyLearningEnvironment
Version: 1.0.1
Summary: A short description of the package
Home-page: https://github.com/edofazza/GameBoyLearningEnvironment
Author: Edoardo Fazzari
Author-email: fazzari.edoardo@gmail.com
Classifier: Programming Language :: Python :: 3
Classifier: License :: OSI Approved :: MIT License
Classifier: Operating System :: OS Independent
Requires-Python: >=3.11
License-File: LICENSE
Requires-Dist: gymnasium
Requires-Dist: numpy==1.26.4
Requires-Dist: pyboy==2.6.0
Requires-Dist: pygame==2.5.2
Requires-Dist: pillow==10.3.0
Requires-Dist: opencv-python==4.10.0.82
